metamart_source_flat_file/__init__.py
metamart_source_flat_file/adapters.py
metamart_source_flat_file/base.py
metamart_source_flat_file/loader.py
metamart_source_flat_file/models.py
metamart_source_flat_file/package_definitions.py
metamart_source_flat_file/yaml.py
metamart_source_flat_file-0.2.2.dist-info/METADATA
metamart_source_flat_file-0.2.2.dist-info/WHEEL
metamart_source_flat_file-0.2.2.dist-info/RECORD
